{"stats":{"minecraft:used":{"minecraft:jukebox":3},"minecraft:mined":{"minecraft:jukebox":2},"minecraft:picked_up":{"minecraft:music_disc_creator":3,"minecraft:jukebox":3},"minecraft:custom":{"minecraft:jump":1,"minecraft:time_since_rest":614,"minecraft:leave_game":1,"minecraft:damage_dealt":10,"minecraft:sprint_one_cm":161,"minecraft:play_record":2,"minecraft:play_time":614,"minecraft:damage_taken":80,"minecraft:time_since_death":614,"minecraft:walk_one_cm":1708,"minecraft:total_world_time":1993,"minecraft:fly_one_cm":160}},"DataVersion":3953}